<?xml version="1.0" encoding="UTF-8"?>
<vv xml:lang="de" xmlns="http://histvv.uni-leipzig.de/ns/2007"
    xmlns:ns="http://histvv.uni-leipzig.de/ns/2007">
  <kopf>
    <universität>Zürich</universität>

    <semester>Sommer</semester>

    <beginn>
      <jahr>1877</jahr>
    </beginn>

    <ende>
      <jahr>1877</jahr>
    </ende>

    <quelle>Verzeichniss der Vorlesungen an der Hochschule Zürich im
    Sommersemester 1877. Anfang am 16. April, Schluss am 18. August 1877,
    Zürich: Zürcher und Furrer, 1877.</quelle>

    <status komplett="ja"/>
  </kopf>

  <titel>Sommersemester 1877</titel>

  <sachgruppe fakultät="Theologie">
    <titel>Theologische Fakultät</titel>

    <veranstaltung xml:id="v-12697"><nr>1</nr> <dozent
    ref="steiner_h"><nachname>Steiner</nachname>, <vorname>Heinrich</vorname>,
    <grad>O</grad></dozent> <thema>Hebräische Archäologie</thema> <zeit>Mo,
    Mi, Fr 8-9</zeit> <wochenstunden>3</wochenstunden></veranstaltung>

    <veranstaltung xml:id="v-12698"><nr>2</nr> <dozent
    ref="egli_k"><nachname>Egli</nachname>, <vorname>Karl</vorname>,
    <grad>PD</grad></dozent> <thema>Ueber den samaritanischen
    Pentateuch</thema> <wochenstunden>2</wochenstunden></veranstaltung>

    <veranstaltung xml:id="v-12699"><nr>3</nr> <dozent
    ref="heidenheim_m"><nachname>Heidenheim</nachname>,
    <vorname>Moritz</vorname>, <grad>PD</grad></dozent> <thema>Erklärung der
    Genesis</thema> <zeit>Di-Do 7-8</zeit>
    <wochenstunden>3</wochenstunden></veranstaltung>

    <veranstaltung xml:id="v-12700"><nr>4</nr> <dozent
    ref="steiner_h"><nachname>Steiner</nachname>, <vorname>Heinrich</vorname>,
    <grad>O</grad></dozent> <thema>Erklärung des Buches Hiob</thema> <zeit>Di,
    Do, Sa 8-9</zeit> <wochenstunden>3</wochenstunden></veranstaltung>

    <veranstaltung xml:id="v-12701"><nr>5</nr> <dozent
    ref="bergen_j"><nachname>Bergen</nachname>, <vorname>Jakob von</vorname>,
    <grad>PD</grad></dozent> <thema>Erklärung des Jesaja</thema> <zeit>Mo, Di,
    Do 15-16</zeit> <wochenstunden>3</wochenstunden></veranstaltung>

    <veranstaltung xml:id="v-12702"><nr>6</nr> <dozent
    ref="kesselring_h"><nachname>Kesselring</nachname>,
    <vorname>Heinrich</vorname>, <grad>O</grad></dozent> <thema>Erklärung des
    Evangeliums nach Lucas und Matthäus mit besonderer Rücksicht auf die
    Reden</thema> <zeit>Mo 9-11, Mi, Sa 10-11</zeit>
    <wochenstunden>4</wochenstunden></veranstaltung>

    <veranstaltung xml:id="v-12703"><nr>7</nr> <dozent
    ref="volkmar_g"><nachname>Volkmar</nachname>, <vorname>Gustav</vorname>,
    <grad>O</grad></dozent> <thema>Erklärung der Apostelgeschichte</thema>
    <zeit>Mo, Mi 15-16, Fr 15-17</zeit>
    <wochenstunden>4</wochenstunden></veranstaltung>

    <veranstaltung xml:id="v-12704"><nr>8</nr> <dozent
    ref="volkmar_g"><nachname>Volkmar</nachname>, <vorname>Gustav</vorname>,
    <grad>O</grad></dozent> <thema>Erklärung des Römerbriefes</thema>
    <zeit>Mo-Fr 7-8</zeit> <wochenstunden>5</wochenstunden></veranstaltung>

    <veranstaltung xml:id="v-12705"><nr>9</nr> <dozent
    ref="bergen_j"><nachname>Bergen</nachname>, <vorname>Jakob von</vorname>,
    <grad>PD</grad></dozent> <thema>Erklärung des Briefes an die
    Galater</thema> <zusatz> <modus>publice</modus> </zusatz> <zeit>Mo
    16-17</zeit> <wochenstunden>1</wochenstunden></veranstaltung>

    <veranstaltung xml:id="v-12706"><nr>10</nr> <dozent
    ref="fritzsche_of"><nachname>Fritzsche</nachname>, <vorname>Otto
    Fridolin</vorname>, <grad>O</grad></dozent> <thema>Kirchengeschichte, II.
    Theil</thema> <zeit>Mo-Fr 11-12</zeit>
    <wochenstunden>5</wochenstunden></veranstaltung>

    <veranstaltung xml:id="v-12707"><nr>11</nr> <dozent
    ref="fritzsche_of"><nachname>Fritzsche</nachname>, <vorname>Otto
    Fridolin</vorname>, <grad>O</grad></dozent> <thema>Kirchengeschichtliches
    Repetitorium</thema> <zeit>Di, Fr 5-6.30</zeit>
    <wochenstunden>3</wochenstunden></veranstaltung>

    <veranstaltung xml:id="v-12708"><nr>12</nr> <dozent
    ref="kesselring_h"><nachname>Kesselring</nachname>,
    <vorname>Heinrich</vorname>, <grad>O</grad></dozent> <thema>Erklärung der
    Confessiones des Augustinus</thema> <zusatz> <modus>publice</modus>
    </zusatz> <wochenstunden>2</wochenstunden></veranstaltung>

    <veranstaltung xml:id="v-12709"><nr>13</nr> <dozent
    ref="schweizer_a"><nachname>Schweizer</nachname>,
    <vorname>Alexander</vorname>, <grad>O</grad>,
    <funktion>Dekan/T</funktion></dozent> <thema>Symbolik</thema> <zeit>Mo,
    Di, Do, Fr 8-9</zeit> <wochenstunden>4</wochenstunden></veranstaltung>

    <veranstaltung xml:id="v-12710"><nr>14</nr> <dozent
    ref="schweizer_a"><nachname>Schweizer</nachname>,
    <vorname>Alexander</vorname>, <grad>O</grad>,
    <funktion>Dekan/T</funktion></dozent> <thema>Dogmengeschichtliches
    Repetitorium</thema> <zeit>Di, Do 15-16</zeit>
    <wochenstunden>2</wochenstunden></veranstaltung>

    <veranstaltung xml:id="v-12711"><nr>15</nr> <dozent
    ref="biedermann_ae"><nachname>Biedermann</nachname>, <vorname>Alois
    Emanuel</vorname>, <grad>O</grad></dozent> <thema>Dogmatik, II. Theil
    (kritisch speculativer Theil)</thema> <zeit>Di-Fr 9-10</zeit>
    <wochenstunden>4</wochenstunden></veranstaltung>

    <veranstaltung xml:id="v-12712"><nr>16</nr> <dozent
    ref="kesselring_h"><nachname>Kesselring</nachname>,
    <vorname>Heinrich</vorname>, <grad>O</grad></dozent>
    <thema>Liturgik</thema> <wochenstunden>2</wochenstunden></veranstaltung>

    <veranstaltung xml:id="v-12713"><nr>17</nr> <dozent
    ref="schweizer_a"><nachname>Schweizer</nachname>,
    <vorname>Alexander</vorname>, <grad>O</grad>,
    <funktion>Dekan/T</funktion></dozent> <thema>Theorie des
    Kirchenregimentes</thema> <zeit>Mi, Sa 8-9</zeit>
    <wochenstunden>2</wochenstunden></veranstaltung>

    <veranstaltung xml:id="v-12714"><nr>18a</nr> <dozent
    ref="steiner_h"><nachname>Steiner</nachname>, <vorname>Heinrich</vorname>,
    <grad>O</grad></dozent> <thema>Uebungen des theologischen Seminars:
    Alttestamentliche Abtheilung: exegetische Uebungen an ausgewählten
    Abschnitten aus den kleinen Propheten</thema> <zusatz>
    <gebühr>unentgeltlich</gebühr> </zusatz> <zeit>Di, Fr 15-16</zeit>
    <wochenstunden>2</wochenstunden></veranstaltung>

    <veranstaltung xml:id="v-12715"><nr>18b</nr> <dozent
    ref="volkmar_g"><nachname>Volkmar</nachname>, <vorname>Gustav</vorname>,
    <grad>O</grad></dozent> <thema>Uebungen des theologischen Seminars:
    Neutestamentliche Abtheilung: exegetische Uebungen am kürzeren
    Lucas-Evangelium Marcions nach Tertullian</thema> <zusatz>
    <gebühr>unentgeltlich</gebühr> </zusatz>
    <wochenstunden>2</wochenstunden></veranstaltung>

    <veranstaltung xml:id="v-12716"><nr>18c</nr> <dozent
    ref="fritzsche_of"><nachname>Fritzsche</nachname>, <vorname>Otto
    Fridolin</vorname>, <grad>O</grad></dozent> <thema>Uebungen des
    theologischen Seminars: Kirchengeschichtliche Abtheilung:
    kirchengeschichtliche Uebungen</thema> <zusatz>
    <gebühr>unentgeltlich</gebühr> </zusatz> <zeit>Do 5-7</zeit>
    <wochenstunden>2</wochenstunden></veranstaltung>

    <veranstaltung xml:id="v-12717"><nr>18d</nr> <dozent
    ref="biedermann_ae"><nachname>Biedermann</nachname>, <vorname>Alois
    Emanuel</vorname>, <grad>O</grad></dozent> <thema>Uebungen des
    theologischen Seminars: Systematisch-theologische Abtheilung: dogmatische
    Uebungen</thema> <zusatz> <gebühr>unentgeltlich</gebühr> </zusatz>
    <wochenstunden>2</wochenstunden></veranstaltung>

    <veranstaltung xml:id="v-12718"><nr>18e</nr> <dozent
    ref="kesselring_h"><nachname>Kesselring</nachname>,
    <vorname>Heinrich</vorname>, <grad>O</grad></dozent> <thema>Uebungen des
    theologischen Seminars: Praktisch-theologische Abtheilung: homiletische
    Uebungen</thema> <zusatz> <gebühr>unentgeltlich</gebühr> </zusatz>
    <wochenstunden>2</wochenstunden></veranstaltung>
  </sachgruppe>

  <sachgruppe fakultät="Staatswissenschaften">
    <titel>Staatswissenschaftliche Fakultät</titel>

    <veranstaltung xml:id="v-12719"><nr>19</nr> <dozent
    ref="orelli_a"><nachname>Orelli</nachname>, <vorname>Aloys von</vorname>,
    <grad>O</grad>, <funktion>Dekan/S</funktion></dozent> <thema>Juristische
    Encyklopädie</thema> <zeit>Di, Do 5-6</zeit>
    <wochenstunden>2</wochenstunden></veranstaltung>

    <veranstaltung xml:id="v-12720"><nr>20</nr> <dozent
    ref="treichler_jj"><nachname>Treichler</nachname>, <vorname>Johann
    Jakob</vorname>, <grad>O</grad></dozent> <thema>Allgemeine
    Rechtslehre</thema> <wochenstunden>3</wochenstunden>
    <ort>Polytechnikum</ort></veranstaltung>

    <veranstaltung xml:id="v-12721"><nr>21</nr> <dozent
    ref="pfenninger_h"><nachname>Pfenninger</nachname>,
    <vorname>Heinrich</vorname>, <grad>PD</grad></dozent> <thema>Grundbegriffe
    des Rechts, entwickelt an den Theorien des Macchiavelli und
    Grotius</thema> <wochenstunden>2</wochenstunden></veranstaltung>

    <veranstaltung xml:id="v-12722"><nr>22</nr> <dozent
    ref="fick_h"><nachname>Fick</nachname>, <vorname>Heinrich</vorname>,
    <grad>O</grad></dozent> <thema>Institutionen des römischen Rechts</thema>
    <zeit>Mo-Do 16-17</zeit> <wochenstunden>4</wochenstunden></veranstaltung>

    <veranstaltung xml:id="v-12723"><nr>23</nr> <dozent
    ref="schneider_a"><nachname>Schneider</nachname>,
    <vorname>Albert</vorname>, <grad>PD</grad></dozent> <thema>Römische
    Rechtsgeschichte</thema> <zeit>Mo-Mi 5-6</zeit>
    <wochenstunden>3</wochenstunden></veranstaltung>

    <veranstaltung xml:id="v-12724"><nr>24</nr> <dozent
    ref="conrat_m"><nachname>Conrat (Cohn)</nachname>, <vorname>Max</vorname>,
    <grad>O</grad></dozent> <thema>Pandekten, I. Theil (Allgemeiner Theil;
    Sachenrecht; Obligationenrecht, allgem. Lehren)</thema> <zeit>Mo-Do 10-12,
    Fr 11-12</zeit> <wochenstunden>9</wochenstunden></veranstaltung>

    <veranstaltung xml:id="v-12725"><nr>25</nr> <dozent
    ref="conrat_m"><nachname>Conrat (Cohn)</nachname>, <vorname>Max</vorname>,
    <grad>O</grad></dozent> <thema>Pandekten-Disputatorium</thema>
    <wochenstunden>2</wochenstunden></veranstaltung>

    <veranstaltung xml:id="v-12726"><nr>26</nr> <dozent
    ref="schneider_a"><nachname>Schneider</nachname>,
    <vorname>Albert</vorname>, <grad>PD</grad></dozent> <thema>Erklärung
    ausgewählter Pandektenstellen</thema> <zeit>Mo 18-20</zeit>
    <wochenstunden>2</wochenstunden></veranstaltung>

    <veranstaltung xml:id="v-12727"><nr>27</nr> <dozent
    ref="schneider_a"><nachname>Schneider</nachname>,
    <vorname>Albert</vorname>, <grad>PD</grad></dozent> <thema>Geschichte des
    römischen Civilprozesses</thema> <zeit>Do 5-7</zeit>
    <wochenstunden>2</wochenstunden></veranstaltung>

    <veranstaltung xml:id="v-12728"><nr>28</nr> <dozent
    ref="orelli_a"><nachname>Orelli</nachname>, <vorname>Aloys von</vorname>,
    <grad>O</grad>, <funktion>Dekan/S</funktion></dozent> <thema>Deutsches
    Privatrecht mit Ausschluss des Lehens- und Handelsrechts nach Krauts
    Grundriss, 5. Auflage<anmerkung>Wilhelm Theodor Kraut, Grundriß zu
    Vorlesungen über das deutsche Privatrecht mit Einschluß des Lehnrechts:
    Nebst beigefügten Quellen, Berlin: Guttentag, ⁵1872.</anmerkung></thema>
    <zeit>Di-Fr 11-12, Sa 9-11</zeit>
    <wochenstunden>6</wochenstunden></veranstaltung>

    <veranstaltung xml:id="v-12729"><nr>29</nr> <dozent
    ref="orelli_a"><nachname>Orelli</nachname>, <vorname>Aloys von</vorname>,
    <grad>O</grad>, <funktion>Dekan/S</funktion></dozent> <thema>Altdeutsches
    Gerichtsverfahren</thema> <wochenstunden>1</wochenstunden></veranstaltung>

    <veranstaltung xml:id="v-12730"><nr>30</nr> <dozent
    ref="osenbrueggen_e"><nachname>Osenbrüggen</nachname>,
    <vorname>Eduard</vorname>, <grad>O</grad></dozent> <thema>Deutsches
    Strafrecht</thema> <zeit>Mo-Do 16-17, Fr 15-17</zeit>
    <wochenstunden>6</wochenstunden></veranstaltung>

    <veranstaltung xml:id="v-12731"><nr>31</nr> <dozent
    ref="osenbrueggen_e"><nachname>Osenbrüggen</nachname>,
    <vorname>Eduard</vorname>, <grad>O</grad></dozent> <thema>Geschichte des
    deutschen Strafrechts</thema> <zeit>Mo, Di 15-16</zeit>
    <wochenstunden>2</wochenstunden></veranstaltung>

    <veranstaltung xml:id="v-12732"><nr>32</nr> <dozent
    ref="temme_j"><nachname>Temme</nachname>, <vorname>Jodokus</vorname>,
    <grad>O</grad></dozent> <thema>Ausgewählte Partieen des Strafrechts und
    Strafprozesses</thema> <wochenstunden>2</wochenstunden></veranstaltung>

    <veranstaltung xml:id="v-12733"><nr>33</nr> <dozent
    ref="temme_j"><nachname>Temme</nachname>, <vorname>Jodokus</vorname>,
    <grad>O</grad></dozent> <thema>Gemeiner deutscher Civilprozess</thema>
    <zeit>Mo-Fr 10-11</zeit> <wochenstunden>5</wochenstunden></veranstaltung>

    <veranstaltung xml:id="v-12734"><nr>34</nr> <dozent
    ref="osenbrueggen_e"><nachname>Osenbrüggen</nachname>,
    <vorname>Eduard</vorname>, <grad>O</grad></dozent> <thema>Die
    gemeinrechtlichen summarischen Processe und das Concursverfahren</thema>
    <zeit>Mi, Do 15-16</zeit> <wochenstunden>2</wochenstunden></veranstaltung>

    <veranstaltung xml:id="v-12735"><nr>35</nr> <dozent
    ref="vogt_g"><nachname>Vogt</nachname>, <vorname>Gustav</vorname>,
    <grad>O</grad>, <funktion>Rektor</funktion></dozent> <thema>Allgemeines
    Staatsrecht</thema> <zeit>Di-Fr 9-10</zeit>
    <wochenstunden>4</wochenstunden></veranstaltung>

    <veranstaltung xml:id="v-12736"><nr>36</nr> <dozent
    ref="orelli_a"><nachname>Orelli</nachname>, <vorname>Aloys von</vorname>,
    <grad>O</grad>, <funktion>Dekan/S</funktion></dozent>
    <thema>Conversatorium über kirchenrechtliche Fragen</thema>
    <wochenstunden>1</wochenstunden></veranstaltung>

    <veranstaltung xml:id="v-12737"><nr>37</nr> <dozent
    ref="fick_h"><nachname>Fick</nachname>, <vorname>Heinrich</vorname>,
    <grad>O</grad></dozent> <thema>Wechselrecht</thema> <zeit>Mi, Do
    15-16</zeit> <wochenstunden>2</wochenstunden></veranstaltung>

    <veranstaltung xml:id="v-12738"><nr>38</nr> <dozent
    ref="fick_h"><nachname>Fick</nachname>, <vorname>Heinrich</vorname>,
    <grad>O</grad></dozent> <thema>Eisenbahnrecht</thema> <zeit>Fr 5-6</zeit>
    <wochenstunden>1</wochenstunden></veranstaltung>

    <veranstaltung xml:id="v-12739"><nr>39</nr> <dozent
    ref="vogt_g"><nachname>Vogt</nachname>, <vorname>Gustav</vorname>,
    <grad>O</grad>, <funktion>Rektor</funktion></dozent> <thema>Recht der
    Gewerbe</thema> <zeit>Mo, Di 18-19</zeit>
    <wochenstunden>2</wochenstunden></veranstaltung>

    <veranstaltung xml:id="v-12740"><nr>40</nr> <dozent
    ref="treichler_jj"><nachname>Treichler</nachname>, <vorname>Johann
    Jakob</vorname>, <grad>O</grad></dozent> <thema>Institutionen des franz.
    Civilrechts</thema> <zeit>Fr, Sa 7-8 &amp; 2h</zeit>
    <wochenstunden>4</wochenstunden></veranstaltung>

    <veranstaltung xml:id="v-12741"><nr>41</nr> <dozent
    ref="fick_h"><nachname>Fick</nachname>, <vorname>Heinrich</vorname>,
    <grad>O</grad></dozent> <thema>Ueber den Entwurf eines schweizerischen
    Obligationenrechts</thema> <zeit>Mo, Di 15-16</zeit>
    <wochenstunden>2</wochenstunden></veranstaltung>

    <veranstaltung xml:id="v-12742"><nr>42</nr> <dozent
    ref="treichler_jj"><nachname>Treichler</nachname>, <vorname>Johann
    Jakob</vorname>, <grad>O</grad></dozent> <thema>Zürcherischer
    Civilprozess</thema> <zeit>Mo-Do 7-8</zeit>
    <wochenstunden>4</wochenstunden></veranstaltung>

    <veranstaltung xml:id="v-12743"><nr>43</nr> <dozent
    ref="vogt_g"><nachname>Vogt</nachname>, <vorname>Gustav</vorname>,
    <grad>O</grad>, <funktion>Rektor</funktion></dozent> <thema>Elemente der
    Nationalökonomie</thema> <zeit>Mo, Mi-Fr 8-9</zeit>
    <wochenstunden>4</wochenstunden></veranstaltung>

    <veranstaltung xml:id="v-12744"><nr>44</nr> <dozent
    ref="contzen_h"><nachname>Contzen</nachname>, <vorname>Heinrich</vorname>,
    <grad>PD</grad></dozent> <thema>Geschichte und Theorie der
    Nationalökonomie</thema> <wochenstunden>2</wochenstunden></veranstaltung>
  </sachgruppe>

  <sachgruppe fakultät="Medizin">
    <titel>Medizinische Fakultät</titel>

    <veranstaltung xml:id="v-12745"><nr>45</nr> <dozent
    ref="frey_h"><nachname>Frey</nachname>, <vorname>Heinrich</vorname>,
    <grad>O</grad></dozent> <thema>Naturgeschichte des Menschen, im
    Polytechnikum</thema> <wochenstunden>2</wochenstunden></veranstaltung>

    <veranstaltung xml:id="v-12746"><nr>46</nr> <dozent
    ref="meyer_gh"><nachname>Meyer</nachname>, <vorname>Georg Hermann
    von</vorname>, <grad>O</grad></dozent> <thema>Osteologie und
    Syndesmologie</thema> <zeit>Mo, Mi, Sa 7-8</zeit>
    <wochenstunden>3</wochenstunden></veranstaltung>

    <veranstaltung xml:id="v-12747"><nr>47</nr> <dozent
    ref="meyer_gh"><nachname>Meyer</nachname>, <vorname>Georg Hermann
    von</vorname>, <grad>O</grad></dozent> <thema>Anatomie des Hirns und der
    Sinnesorgane</thema> <zeit>Mi, Sa 9-10</zeit>
    <wochenstunden>2</wochenstunden></veranstaltung>

    <veranstaltung xml:id="v-12748"><nr>48</nr> <dozent
    ref="meyer_gh"><nachname>Meyer</nachname>, <vorname>Georg Hermann
    von</vorname>, <grad>O</grad></dozent> <thema>Topographische
    Anatomie</thema> <zeit>Di, Do, Fr 14-15</zeit>
    <wochenstunden>3</wochenstunden></veranstaltung>

    <veranstaltung xml:id="v-12749"><nr>49</nr> <dozent
    ref="meyer_gh"><nachname>Meyer</nachname>, <vorname>Georg Hermann
    von</vorname>, <grad>O</grad></dozent> <thema>Statik und Mechanik des
    Knochengerüstes mit Rücksicht auf Orthopädie</thema> <zeit>Mo, Mi
    14-15</zeit> <wochenstunden>2</wochenstunden></veranstaltung>

    <veranstaltung xml:id="v-12750"><nr>50</nr> <dozent
    ref="frey_h"><nachname>Frey</nachname>, <vorname>Heinrich</vorname>,
    <grad>O</grad></dozent> <thema>Vergleichende Anatomie</thema> <zeit>Mo,
    Di, Do, Fr 9-10</zeit> <wochenstunden>4</wochenstunden></veranstaltung>

    <veranstaltung xml:id="v-12751"><nr>51</nr> <dozent
    ref="frey_h"><nachname>Frey</nachname>, <vorname>Heinrich</vorname>,
    <grad>O</grad></dozent> <thema>Mikroskopisches Praktikum</thema> <zeit>2x
    ab 2</zeit></veranstaltung>

    <veranstaltung xml:id="v-12752"><nr>52</nr> <dozent
    ref="frey_h"><nachname>Frey</nachname>, <vorname>Heinrich</vorname>,
    <grad>O</grad></dozent> <thema>Zootomischer Uebungscurs</thema>
    <wochenstunden>3</wochenstunden></veranstaltung>

    <veranstaltung xml:id="v-12753"><nr>53</nr> <dozent
    ref="hermann_l"><nachname>Hermann</nachname>, <vorname>Ludimar</vorname>,
    <grad>O</grad></dozent> <thema>Erste Hälfte der
    Experimentalphysiologie</thema> <zeit>Mo-Sa 8-9</zeit>
    <wochenstunden>6</wochenstunden></veranstaltung>

    <veranstaltung xml:id="v-12754"><nr>54</nr> <dozent
    ref="hermann_l"><nachname>Hermann</nachname>, <vorname>Ludimar</vorname>,
    <grad>O</grad></dozent> <thema>Physiologie der Sinnesorgane (Optik,
    Akustik etc.)</thema> <zeit>Di 5-7, Fr 5-6</zeit>
    <wochenstunden>3</wochenstunden></veranstaltung>

    <veranstaltung xml:id="v-12755"><nr>55</nr> <dozent
    ref="hermann_l"><nachname>Hermann</nachname>, <vorname>Ludimar</vorname>,
    <grad>O</grad></dozent> <thema>Hygieine auf physiologischer
    Grundlage</thema> <zusatz>für Zuhörer aller Fakultäten</zusatz>
    <wochenstunden>2</wochenstunden></veranstaltung>

    <veranstaltung xml:id="v-12756"><nr>56</nr> <dozent
    ref="hermann_l"><nachname>Hermann</nachname>, <vorname>Ludimar</vorname>,
    <grad>O</grad></dozent> <thema>Arbeiten im physiologischen
    Laboratorium</thema> <zeit>Mo-Sa</zeit></veranstaltung>

    <veranstaltung xml:id="v-12757"><nr>57</nr> <dozent
    ref="luchsinger_b"><nachname>Luchsinger</nachname>,
    <vorname>Balthasar</vorname>, <grad>PD</grad></dozent>
    <thema>Physiologische Chemie</thema>
    <wochenstunden>2</wochenstunden></veranstaltung>

    <veranstaltung xml:id="v-12758"><nr>58</nr> <dozent
    ref="eberth_kj"><nachname>Eberth</nachname>, <vorname>Karl
    Joseph</vorname>, <grad>O</grad>, <funktion>Dekan/M</funktion></dozent>
    <thema>Specielle pathologische Anatomie</thema> <zeit>Mo-Fr 15-16</zeit>
    <wochenstunden>5</wochenstunden></veranstaltung>

    <veranstaltung xml:id="v-12759"><nr>59</nr> <dozent
    ref="eberth_kj"><nachname>Eberth</nachname>, <vorname>Karl
    Joseph</vorname>, <grad>O</grad>, <funktion>Dekan/M</funktion></dozent>
    <thema>Praktikum der pathologischen Histologie</thema> <zeit>Fr
    8-11</zeit> <wochenstunden>3</wochenstunden></veranstaltung>

    <veranstaltung xml:id="v-12760"><nr>60</nr> <dozent
    ref="eberth_kj"><nachname>Eberth</nachname>, <vorname>Karl
    Joseph</vorname>, <grad>O</grad>, <funktion>Dekan/M</funktion></dozent>
    <thema>Secirübungen</thema> <zeit>Mo, Fr 16-18</zeit>
    <wochenstunden>4</wochenstunden></veranstaltung>

    <veranstaltung xml:id="v-12761"><nr>61</nr> <dozent
    ref="eberth_kj"><nachname>Eberth</nachname>, <vorname>Karl
    Joseph</vorname>, <grad>O</grad>, <funktion>Dekan/M</funktion></dozent>
    <thema>Arbeiten im pathologischen Institut</thema></veranstaltung>

    <veranstaltung xml:id="v-12762"><nr>62</nr> <dozent
    ref="cloetta_a"><nachname>Cloetta</nachname>, <vorname>Arnold</vorname>,
    <grad>O</grad></dozent> <thema>Allgemeine Pathologie</thema> <zeit>Mo, Di,
    Do, Fr 16-17</zeit> <wochenstunden>4</wochenstunden></veranstaltung>

    <veranstaltung xml:id="v-12763"><nr>63</nr> <dozent
    ref="cloetta_a"><nachname>Cloetta</nachname>, <vorname>Arnold</vorname>,
    <grad>O</grad></dozent> <thema>Pharmakologische Uebungen</thema> <zeit>Mi
    5-6</zeit> <wochenstunden>1</wochenstunden></veranstaltung>

    <veranstaltung xml:id="v-12764"><nr>64</nr> <dozent
    ref="cloetta_a"><nachname>Cloetta</nachname>, <vorname>Arnold</vorname>,
    <grad>O</grad></dozent> <thema>Heilquellenlehre</thema> <zeit>Di, Fr
    5-6</zeit> <wochenstunden>2</wochenstunden></veranstaltung>

    <veranstaltung xml:id="v-12765"><nr>65</nr> <dozent
    ref="goll_f"><nachname>Goll</nachname>, <vorname>Friedrich</vorname>,
    <grad>PD</grad></dozent> <thema>Specielle Arzneimittellehre mit
    Vorweisungen</thema> <zeit>Mo, Di, Do, Fr 5-6</zeit>
    <wochenstunden>4</wochenstunden></veranstaltung>

    <veranstaltung xml:id="v-12766"><nr>66</nr> <dozent
    ref="seitz_j"><nachname>Seitz</nachname>, <vorname>Johannes</vorname>,
    <grad>PD</grad></dozent> <thema>Elektrotherapie</thema>
    <wochenstunden>1</wochenstunden></veranstaltung>

    <veranstaltung xml:id="v-12767"><nr>67</nr> <dozent
    ref="huguenin_g"><nachname>Huguenin</nachname>, <vorname>Gustav</vorname>,
    <grad>O</grad></dozent> <thema>Medicinische Klinik</thema> <zeit>Mo-Do, Sa
    9-10.30</zeit> <wochenstunden>7.5</wochenstunden></veranstaltung>

    <veranstaltung xml:id="v-12768"><nr>68</nr> <dozent
    ref="huguenin_g"><nachname>Huguenin</nachname>, <vorname>Gustav</vorname>,
    <grad>O</grad></dozent> <thema>Phthisis pulmonum</thema> <zusatz>
    <modus>publice</modus> </zusatz>
    <wochenstunden>1.5</wochenstunden></veranstaltung>

    <veranstaltung xml:id="v-12769"><nr>69</nr> <dozent
    ref="huguenin_g"><nachname>Huguenin</nachname>, <vorname>Gustav</vorname>,
    <grad>O</grad></dozent> <thema>Krankheiten der Pleura</thema> <zusatz>
    <modus>publice</modus> </zusatz>
    <wochenstunden>1.5</wochenstunden></veranstaltung>

    <veranstaltung xml:id="v-12770"><nr>70</nr> <dozent
    ref="wyss-kienast_o"><nachname>Wyss-Kienast</nachname>,
    <vorname>Oscar</vorname>, <grad>EO</grad></dozent> <thema>Specielle
    Pathologie und Therapie</thema> <zeit>Mo-Fr 7-8</zeit>
    <wochenstunden>5</wochenstunden></veranstaltung>

    <veranstaltung xml:id="v-12771"><nr>71</nr> <dozent
    ref="seitz_j"><nachname>Seitz</nachname>, <vorname>Johannes</vorname>,
    <grad>PD</grad></dozent> <thema>Specielle Pathologie und Therapie,
    allgemeine Ernährungsstörungen, mit klinischen Demonstrationen</thema>
    <zeit>Mo-Mi 7-8</zeit> <wochenstunden>3</wochenstunden></veranstaltung>

    <veranstaltung xml:id="v-12772"><nr>72</nr> <dozent
    ref="rose_e"><nachname>Rose</nachname>, <vorname>Edmund</vorname>,
    <grad>O</grad></dozent> <thema>Specielle Chirurgie und
    Operationslehre</thema> <zeit>Mo, Mi-Sa 8-9</zeit>
    <wochenstunden>5</wochenstunden></veranstaltung>

    <veranstaltung xml:id="v-12773"><nr>73</nr> <dozent
    ref="rose_e"><nachname>Rose</nachname>, <vorname>Edmund</vorname>,
    <grad>O</grad></dozent> <thema>Chirurgische Klinik und Poliklinik</thema>
    <zeit>Mo, Mi-Sa 10.30-12</zeit>
    <wochenstunden>7.5</wochenstunden></veranstaltung>

    <veranstaltung xml:id="v-12774"><nr>74</nr> <dozent
    ref="rose_e"><nachname>Rose</nachname>, <vorname>Edmund</vorname>,
    <grad>O</grad></dozent> <thema>Chirurgischer Operationscurs</thema>
    <zeit>Di 6-10 evtl. 6-12, Fr 6-8</zeit>
    <wochenstunden>6-8</wochenstunden></veranstaltung>

    <veranstaltung xml:id="v-12775"><nr>75</nr> <dozent
    ref="frankenhaeuser_f"><nachname>Frankenhäuser</nachname>,
    <vorname>Ferdinand</vorname>, <grad>O</grad></dozent> <thema>Klinik für
    Geburtshülfe und Gynäkologie</thema> <zeit>Mo-Sa 14-15</zeit>
    <wochenstunden>6</wochenstunden></veranstaltung>

    <veranstaltung xml:id="v-12776"><nr>76</nr> <dozent
    ref="frankenhaeuser_f"><nachname>Frankenhäuser</nachname>,
    <vorname>Ferdinand</vorname>, <grad>O</grad></dozent>
    <thema>Frauenkrankheiten</thema> <zeit>Mo, Di, Do, Fr 16-17</zeit>
    <wochenstunden>4</wochenstunden></veranstaltung>

    <veranstaltung xml:id="v-12777"><nr>77</nr> <dozent
    ref="frankenhaeuser_f"><nachname>Frankenhäuser</nachname>,
    <vorname>Ferdinand</vorname>, <grad>O</grad></dozent>
    <thema>Geburtshülflicher Operationscurs</thema> <zeit>Mo, Di, Do, Fr 5-6
    evtl. 5-7</zeit> <wochenstunden>4-8</wochenstunden></veranstaltung>

    <veranstaltung xml:id="v-12778"><nr>78</nr> <dozent
    ref="spoendly_h"><nachname>Spöndly</nachname>,
    <vorname>Heinrich</vorname>, <grad>EO</grad></dozent> <thema>Theoretische
    Geburtshülfe</thema> <zeit>Mo, Di, Do, Fr 15-16</zeit>
    <wochenstunden>4</wochenstunden></veranstaltung>

    <veranstaltung xml:id="v-12779"><nr>79</nr> <dozent
    ref="hitzig_e"><nachname>Hitzig</nachname>, <vorname>Eduard</vorname>,
    <grad>O</grad></dozent> <thema>Psychiatrie und psychiatrische
    Klinik</thema> <zeit>Mi, Sa 14.30-16</zeit>
    <wochenstunden>3</wochenstunden></veranstaltung>

    <veranstaltung xml:id="v-12780"><nr>80</nr> <dozent
    ref="horner_jf"><nachname>Horner</nachname>, <vorname>Johann
    Friedrich</vorname>, <grad>O</grad></dozent> <thema>Ophthalmologische
    Klinik und Poliklinik</thema> <zeit>Di, Do, Sa 8-9</zeit>
    <wochenstunden>3</wochenstunden></veranstaltung>

    <veranstaltung xml:id="v-12781"><nr>81</nr> <dozent
    ref="horner_jf"><nachname>Horner</nachname>, <vorname>Johann
    Friedrich</vorname>, <grad>O</grad></dozent> <thema>Die Lehre von den
    Anomalien der Refraction und Accommodation</thema> <zeit>Mi, Fr 8-9</zeit>
    <wochenstunden>2</wochenstunden></veranstaltung>

    <veranstaltung xml:id="v-12782"><nr>82</nr> <dozent
    ref="horner_jf"><nachname>Horner</nachname>, <vorname>Johann
    Friedrich</vorname>, <grad>O</grad></dozent> <thema>Die Augenkrankheiten
    des Kindesalters, Fortsetzung</thema> <zusatz> <modus>publice</modus>
    </zusatz> <wochenstunden>2</wochenstunden></veranstaltung>

    <veranstaltung xml:id="v-12783"><nr>83</nr> <dozent
    ref="wyss-kienast_o"><nachname>Wyss-Kienast</nachname>,
    <vorname>Oscar</vorname>, <grad>EO</grad></dozent> <thema>Poliklinik, im
    Kantonsspital</thema> <zeit>Mo-Sa 15-16</zeit>
    <wochenstunden>6</wochenstunden></veranstaltung>

    <veranstaltung xml:id="v-12784"><nr>84</nr> <dozent
    ref="wyss-kienast_o"><nachname>Wyss-Kienast</nachname>,
    <vorname>Oscar</vorname>, <grad>EO</grad></dozent> <thema>Pädiatrische
    Klinik, im Kinderspital</thema> <zeit>Di 10.45-12, Fr 9.30-10.45</zeit>
    <wochenstunden>3</wochenstunden></veranstaltung>

    <veranstaltung xml:id="v-12785"><nr>85</nr> <dozent
    ref="wyss-kienast_o"><nachname>Wyss-Kienast</nachname>,
    <vorname>Oscar</vorname>, <grad>EO</grad></dozent> <thema>Allgemeine
    Pathologie und Hygiene des Kindesalters</thema> <zeit>Di, Do 16-17</zeit>
    <wochenstunden>2</wochenstunden></veranstaltung>

    <veranstaltung xml:id="v-12786"><nr>86</nr> <dozent
    ref="meyer-hueni_r"><nachname>Meyer-Hueni</nachname>,
    <vorname>Rudolf</vorname>, <grad>PD</grad></dozent> <thema>Krankheiten der
    ersten Luft- und Speisewege (Nase, Rachen, Kehlkopf etc.) mit
    laryngoscopischem Curs</thema>
    <wochenstunden>2</wochenstunden></veranstaltung>

    <veranstaltung xml:id="v-12787"><nr>87</nr> <dozent
    ref="seitz_j"><nachname>Seitz</nachname>, <vorname>Johannes</vorname>,
    <grad>PD</grad></dozent> <thema>Hautkrankheiten und Syphilis</thema>
    <zeit>Di 10.30-12</zeit>
    <wochenstunden>1.5</wochenstunden></veranstaltung>

    <veranstaltung xml:id="v-12788"><nr>88</nr> <dozent
    ref="billeter_j"><nachname>Billeter</nachname>, <vorname>Jakob</vorname>,
    <grad>PD</grad></dozent> <thema>Zahnärztlicher Operationscurs</thema>
    <wochenstunden>2</wochenstunden></veranstaltung>
  </sachgruppe>

  <sachgruppe fakultät="Philosophie">
    <titel>Philosophische Fakultät</titel>

    <sachgruppe>
      <titel>Philosophisch-philologisch-historische Section</titel>

      <sachgruppe>
        <titel>Philosophie</titel>

        <veranstaltung xml:id="v-12789"><nr>89</nr> <dozent
        ref="kym_al"><nachname>Kym</nachname>, <vorname>Andreas
        Ludwig</vorname>, <grad>O</grad></dozent> <thema>Hauptprobleme der
        Philosophie, im Anschluss an seine metaphysischen
        Untersuchungen</thema>
        <wochenstunden>2</wochenstunden></veranstaltung>

        <veranstaltung xml:id="v-12790"><nr>90</nr> <dozent
        ref="kym_al"><nachname>Kym</nachname>, <vorname>Andreas
        Ludwig</vorname>, <grad>O</grad></dozent> <thema>Psychologie</thema>
        <zeit>Mo-Mi 11-12</zeit>
        <wochenstunden>3</wochenstunden></veranstaltung>

        <veranstaltung xml:id="v-12791"><nr>91</nr> <dozent
        ref="fehr_d"><nachname>Fehr</nachname>, <vorname>Daniel</vorname>,
        <grad>PD</grad></dozent> <thema>Pädagogik</thema>
        <wochenstunden>3</wochenstunden></veranstaltung>

        <veranstaltung xml:id="v-12792"><nr>92</nr> <dozent
        ref="kym_al"><nachname>Kym</nachname>, <vorname>Andreas
        Ludwig</vorname>, <grad>O</grad></dozent> <thema>Darstellung und
        Kritik der Philosophie von Cartesius bis Kant</thema> <zeit>Mo-Mi
        5-6</zeit> <wochenstunden>3</wochenstunden></veranstaltung>

        <veranstaltung xml:id="v-12793"><nr>93</nr> <dozent
        ref="kym_al"><nachname>Kym</nachname>, <vorname>Andreas
        Ludwig</vorname>, <grad>O</grad></dozent> <thema>Philosophische
        Uebungen mit Bezug auf das erste Buch der aristotelischen Metaphysik,
        Fortsetzung</thema> <zeit>Mo 6-8</zeit>
        <wochenstunden>2</wochenstunden></veranstaltung>
      </sachgruppe>

      <sachgruppe>
        <titel>Sprach- und Alterthumswissenschaft, Literaturgeschichte</titel>

        <veranstaltung xml:id="v-12794"><nr>94</nr> <dozent
        ref="tobler_jl"><nachname>Tobler</nachname>, <vorname>Johann
        Ludwig</vorname>, <grad>EO</grad></dozent> <thema>Allgemeine
        Sprachwissenschaft, I. Theil: Ursprung und Wesen der Sprache</thema>
        <zeit>Mo, Do 15-16</zeit>
        <wochenstunden>2</wochenstunden></veranstaltung>

        <veranstaltung xml:id="v-12795"><nr>95</nr> <dozent
        ref="schweizer-sidler_h"><nachname>Schweizer-Sidler</nachname>,
        <vorname>Heinrich</vorname>, <grad>O</grad></dozent> <thema>Zweiter
        Sanskritcurs</thema> <zeit>Di, Mi, Fr 6-7</zeit>
        <wochenstunden>3</wochenstunden></veranstaltung>

        <veranstaltung xml:id="v-12796"><nr>96</nr> <dozent
        ref="schweizer-sidler_h"><nachname>Schweizer-Sidler</nachname>,
        <vorname>Heinrich</vorname>, <grad>O</grad></dozent> <thema>Kâlidâsa's
        Mêghadûta (ed. Stenzler)<anmerkung>Meghadûta der Wolkenbote: Gedicht
        von Kâlidâsa, hg. von Adolf Friedrich Stenzler, Breslau: Mälzer,
        1874.</anmerkung></thema> <zeit>Mo, Do 6-7</zeit>
        <wochenstunden>2</wochenstunden></veranstaltung>

        <veranstaltung xml:id="v-12797"><nr>97</nr> <dozent
        ref="heidenheim_m"><nachname>Heidenheim</nachname>,
        <vorname>Moritz</vorname>, <grad>PD</grad></dozent> <thema>Syrische
        Sprache</thema> <zeit>Di, Do 5-6</zeit>
        <wochenstunden>2</wochenstunden></veranstaltung>

        <veranstaltung xml:id="v-12798"><nr>98</nr> <dozent
        ref="steiner_h"><nachname>Steiner</nachname>,
        <vorname>Heinrich</vorname>, <grad>O</grad></dozent> <thema>Arabische
        Sprache: Formenlehre mit Leseübungen im Koran</thema> <zeit>Di, Fr
        16-17</zeit> <wochenstunden>2</wochenstunden></veranstaltung>

        <veranstaltung xml:id="v-12799"><nr>99</nr> <dozent
        ref="steiner_h"><nachname>Steiner</nachname>,
        <vorname>Heinrich</vorname>, <grad>O</grad></dozent> <thema>Türkische
        Sprache</thema> <zeit>Sa 9-10</zeit>
        <wochenstunden>1</wochenstunden></veranstaltung>

        <veranstaltung xml:id="v-12800"><nr>100</nr> <dozent
        ref="kaegi_a"><nachname>Kaegi</nachname>, <vorname>Adolf</vorname>,
        <grad>PD</grad></dozent> <thema>Das Verbum der griechischen
        Sprache</thema> <wochenstunden>2</wochenstunden></veranstaltung>

        <veranstaltung xml:id="v-12801"><nr>101</nr> <dozent
        ref="schweizer-sidler_h"><nachname>Schweizer-Sidler</nachname>,
        <vorname>Heinrich</vorname>, <grad>O</grad></dozent>
        <thema>Darstellung des altitalischen Verbums und einzelner Punkte der
        lateinischen Syntax</thema> <zeit>Mo, Mi, Fr 5-6</zeit>
        <wochenstunden>3</wochenstunden></veranstaltung>

        <veranstaltung xml:id="v-12802"><nr>102</nr> <dozent
        ref="kinkel_g"><nachname>Kinkel</nachname>,
        <vorname>Gottfried</vorname>, <grad>PD</grad></dozent>
        <thema>Erklärung von Euripides' Phönissen</thema> <zeit>Mo, Do
        9-10</zeit> <wochenstunden>2</wochenstunden></veranstaltung>

        <veranstaltung xml:id="v-12803"><nr>103</nr> <dozent
        ref="dilthey_k"><nachname>Dilthey</nachname>, <vorname>Karl</vorname>,
        <grad>O</grad>, <funktion>Dekan/P1</funktion></dozent>
        <thema>Erklärung der Idyllien Theokrits</thema> <zeit>Mo, Mi, Fr
        11-12</zeit> <wochenstunden>3</wochenstunden></veranstaltung>

        <veranstaltung xml:id="v-12804"><nr>104</nr> <dozent
        ref="hug_a"><nachname>Hug</nachname>, <vorname>Arnold</vorname>,
        <grad>O</grad></dozent> <thema>Lectüre griechischer Dichter</thema>
        <zeit>Di 8-10</zeit> <wochenstunden>2</wochenstunden></veranstaltung>

        <veranstaltung xml:id="v-12805"><nr>105</nr> <dozent
        ref="schweizer-sidler_h"><nachname>Schweizer-Sidler</nachname>,
        <vorname>Heinrich</vorname>, <grad>O</grad></dozent> <thema>Abschnitte
        aus Ovids Metamorphosen</thema> <zeit>Di, Do 17-18</zeit>
        <wochenstunden>2</wochenstunden></veranstaltung>

        <veranstaltung xml:id="v-12806"><nr>106</nr> <dozent
        ref="hug_a"><nachname>Hug</nachname>, <vorname>Arnold</vorname>,
        <grad>O</grad></dozent> <thema>Römische Literaturgeschichte, II.
        Theil, von der Sullanischen Zeit an</thema> <zeit>Mo, Do, Fr
        7-8</zeit> <wochenstunden>3</wochenstunden></veranstaltung>

        <veranstaltung xml:id="v-12807"><nr>107</nr> <dozent
        ref="hug_a"><nachname>Hug</nachname>, <vorname>Arnold</vorname>,
        <grad>O</grad></dozent> <thema>Die neueren Forschungen über Cäsars
        gallischen Krieg, mit Excursen über das griechisch-römische
        Kriegswesen</thema> <zeit>Mo, Do, Fr 8-9</zeit>
        <wochenstunden>3</wochenstunden></veranstaltung>

        <veranstaltung xml:id="v-12808"><nr>108</nr> <dozent
        ref="dilthey_k"><nachname>Dilthey</nachname>, <vorname>Karl</vorname>,
        <grad>O</grad>, <funktion>Dekan/P1</funktion></dozent>
        <thema>Archäologische Uebungen</thema> <zeit>Di 10-12</zeit>
        <wochenstunden>2</wochenstunden></veranstaltung>

        <veranstaltung xml:id="v-12809"><nr>109</nr> <dozent
        ref="dilthey_k"><nachname>Dilthey</nachname>, <vorname>Karl</vorname>,
        <grad>O</grad>, <funktion>Dekan/P1</funktion></dozent>
        <thema>Erklärung der Abgüsse im archäologischen Museum</thema>
        <zeit>Do 11-12</zeit> <wochenstunden>1</wochenstunden></veranstaltung>

        <veranstaltung xml:id="v-12810"><nr>110a</nr> <dozent
        ref="schweizer-sidler_h"><nachname>Schweizer-Sidler</nachname>,
        <vorname>Heinrich</vorname>, <grad>O</grad></dozent>
        <thema>Philologisch-pädagogisches Seminar: Sprachwissenschaftliche
        Uebungen</thema> <zeit>Sa 10-12</zeit>
        <wochenstunden>2</wochenstunden></veranstaltung>

        <veranstaltung xml:id="v-12811"><nr>110b</nr> <dozent
        ref="hug_a"><nachname>Hug</nachname>, <vorname>Arnold</vorname>,
        <grad>O</grad></dozent> <thema>Philologisch-pädagogisches Seminar:
        Interpretation von Xenophons Symposion, philologische Arbeiten,
        griechische Stilübungen</thema> <zeit>Mi 18-20</zeit>
        <wochenstunden>2</wochenstunden></veranstaltung>

        <veranstaltung xml:id="v-12812"><nr>110c</nr> <dozent
        ref="dilthey_k"><nachname>Dilthey</nachname>, <vorname>Karl</vorname>,
        <grad>O</grad>, <funktion>Dekan/P1</funktion></dozent>
        <thema>Philologisch-pädagogisches Seminar: Interpretation der letzten
        Elegie des Properz, philologische Arbeiten, lateinische
        Stilübungen</thema> <zeit>Fr 18-20</zeit>
        <wochenstunden>2</wochenstunden></veranstaltung>

        <veranstaltung xml:id="v-12813"><nr>111</nr> <dozent
        ref="ettmueller_eml"><nachname>Ettmüller</nachname>, <vorname>Ernst
        Moritz Ludwig</vorname>, <grad>EO</grad></dozent> <thema>Erklärung
        ausgewählter Eddalieder (Fortsetzung)</thema> <zeit>Mo, Mi
        14.30-16</zeit> <wochenstunden>3</wochenstunden></veranstaltung>

        <veranstaltung xml:id="v-12814"><nr>112</nr> <dozent
        ref="tobler_jl"><nachname>Tobler</nachname>, <vorname>Johann
        Ludwig</vorname>, <grad>EO</grad></dozent> <thema>Mittelhochdeutsche
        Lyriker</thema> <zeit>Di, Fr 15-16</zeit>
        <wochenstunden>2</wochenstunden></veranstaltung>

        <veranstaltung xml:id="v-12815"><nr>113</nr> <dozent
        ref="ettmueller_eml"><nachname>Ettmüller</nachname>, <vorname>Ernst
        Moritz Ludwig</vorname>, <grad>EO</grad></dozent> <thema>Anleitung zur
        kritischen Behandlung mittelhochdeutscher Gedichte, besonders
        epischer, mit Uebungen</thema> <zeit>Di, Do 14.30-16</zeit>
        <wochenstunden>3</wochenstunden></veranstaltung>

        <veranstaltung xml:id="v-12816"><nr>114</nr> <dozent
        ref="honegger_jj"><nachname>Honegger</nachname>, <vorname>Johann
        Jacob</vorname>, <grad>EO</grad></dozent> <thema>Geschichte der
        deutschen Literatur und Sprache, von den Anfängen bis auf
        Luther</thema> <zeit>Di 10-11, Do 9-11</zeit>
        <wochenstunden>3</wochenstunden></veranstaltung>

        <veranstaltung xml:id="v-12817"><nr>115</nr> <dozent
        ref="voegelin_fs"><nachname>Vögelin</nachname>, <vorname>Friedrich
        Salomon</vorname>, <grad>O</grad></dozent> <thema>Herder's Leben und
        Schriften</thema> <wochenstunden>2</wochenstunden></veranstaltung>

        <veranstaltung xml:id="v-12818"><nr>116</nr> <dozent
        ref="stiefel_j"><nachname>Stiefel</nachname>,
        <vorname>Julius</vorname>, <grad>PD</grad></dozent> <thema>Schiller's
        Dramen, literar-historisch und ästhetisch-kritisch erläutert</thema>
        <wochenstunden>2</wochenstunden></veranstaltung>

        <veranstaltung xml:id="v-12819"><nr>117</nr> <dozent
        ref="jacoby_d"><nachname>Jacoby</nachname>, <vorname>Daniel</vorname>,
        <grad>PD</grad></dozent> <thema>Ueber Schillers ästhetische und
        philosophische Schriften</thema> <zeit>Di 14-16</zeit>
        <wochenstunden>2</wochenstunden></veranstaltung>

        <veranstaltung xml:id="v-12820"><nr>118</nr> <dozent
        ref="stiefel_j"><nachname>Stiefel</nachname>,
        <vorname>Julius</vorname>, <grad>PD</grad></dozent> <thema>Deutsche
        Dramatiker des XIX. Jahrhunderts</thema>
        <wochenstunden>2</wochenstunden></veranstaltung>

        <veranstaltung xml:id="v-12821"><nr>119</nr> <dozent
        ref="honegger_jj"><nachname>Honegger</nachname>, <vorname>Johann
        Jacob</vorname>, <grad>EO</grad></dozent>
        <thema>Stilistisch-rhetorische Uebungen</thema> <zeit>Di 8-9</zeit>
        <wochenstunden>1</wochenstunden></veranstaltung>

        <veranstaltung xml:id="v-12822"><nr>120</nr> <dozent
        ref="tobler_jl"><nachname>Tobler</nachname>, <vorname>Johann
        Ludwig</vorname>, <grad>EO</grad></dozent> <thema>Rätoromanische
        Sprache und Literatur</thema> <zeit>Mi 15-16</zeit>
        <wochenstunden>1</wochenstunden></veranstaltung>

        <veranstaltung xml:id="v-12823"><nr>121</nr> <dozent
        ref="breitinger_h"><nachname>Breitinger</nachname>,
        <vorname>Heinrich</vorname>, <grad>O</grad></dozent> <thema>Uebersicht
        der spanischen Formenlehre als Anleitung zur Lectüre von Guillen de
        Castro's Drama: "Las mocedades del Cid" und Vergleichung dieses
        Stückes mit Corneille's Cid</thema> <zeit>Mi, Do 5-6</zeit>
        <wochenstunden>2</wochenstunden></veranstaltung>

        <veranstaltung xml:id="v-12824"><nr>122</nr> <dozent
        ref="breitinger_h"><nachname>Breitinger</nachname>,
        <vorname>Heinrich</vorname>, <grad>O</grad></dozent> <thema>Molière
        und seine Werke</thema> <zeit>Mo 5-6</zeit>
        <wochenstunden>1</wochenstunden></veranstaltung>

        <veranstaltung xml:id="v-12825"><nr>123</nr> <dozent
        ref="breitinger_h"><nachname>Breitinger</nachname>,
        <vorname>Heinrich</vorname>, <grad>O</grad></dozent>
        <thema>Shakspear's Julius Cäsar</thema> <zeit>Do 6-7</zeit>
        <wochenstunden>1</wochenstunden></veranstaltung>

        <veranstaltung xml:id="v-12826"><nr>124</nr> <dozent
        ref="breitinger_h"><nachname>Breitinger</nachname>,
        <vorname>Heinrich</vorname>, <grad>O</grad></dozent>
        <thema>Französischer Curs (Lecture, Uebersetzungen, Stylübungen,
        Interpretation von Boileau's art poétique)</thema> <zeit>Mo-Mi, Fr
        6-7</zeit> <wochenstunden>4</wochenstunden></veranstaltung>

        <veranstaltung xml:id="v-12827"><nr>125</nr> <dozent
        ref="breitinger_h"><nachname>Breitinger</nachname>,
        <vorname>Heinrich</vorname>, <grad>O</grad></dozent> <thema>Englischer
        Elementarcurs</thema> <zeit>Di, Fr 5-6</zeit>
        <wochenstunden>2</wochenstunden></veranstaltung>
      </sachgruppe>

      <sachgruppe>
        <titel>Geschichte, Kunstgeschichte</titel>

        <veranstaltung xml:id="v-12828"><nr>126</nr> <dozent
        ref="biedermann_ae"><nachname>Biedermann</nachname>, <vorname>Alois
        Emanuel</vorname>, <grad>O</grad></dozent> <thema>Allgemeine
        Religionsgeschichte</thema> <zeit>Di-Fr 10-11</zeit>
        <wochenstunden>4</wochenstunden></veranstaltung>

        <veranstaltung xml:id="v-12829"><nr>127</nr> <dozent
        ref="mueller_j"><nachname>Müller</nachname>, <vorname>Jakob</vorname>,
        <grad>O</grad></dozent> <thema>Alte Geschichte, von den Perserkriegen
        bis zum Untergang des weströmischen Reiches</thema> <zeit>Mi-Fr
        9-10</zeit> <wochenstunden>3</wochenstunden></veranstaltung>

        <veranstaltung xml:id="v-12830"><nr>128</nr> <dozent
        ref="kinkel_g"><nachname>Kinkel</nachname>,
        <vorname>Gottfried</vorname>, <grad>PD</grad></dozent> <thema>Die
        geistige Entwicklung des Hellenenthums bis auf Alexander</thema>
        <zeit>Di, Fr 15-16</zeit>
        <wochenstunden>2</wochenstunden></veranstaltung>

        <veranstaltung xml:id="v-12831"><nr>129</nr> <dozent
        ref="mueller_j"><nachname>Müller</nachname>, <vorname>Jakob</vorname>,
        <grad>O</grad></dozent> <thema>Lateinische Epigraphik mit
        Uebungen</thema> <zeit>Mo 9-11, Mi 10-11</zeit>
        <wochenstunden>3</wochenstunden></veranstaltung>

        <veranstaltung xml:id="v-12832"><nr>130</nr> <dozent
        ref="mueller_j"><nachname>Müller</nachname>, <vorname>Jakob</vorname>,
        <grad>O</grad></dozent> <thema>Die hervorragendsten Erscheinungen der
        antiken und modernen Geschichtsschreibung</thema>
        <wochenstunden>2</wochenstunden></veranstaltung>

        <veranstaltung xml:id="v-12833"><nr>131</nr> <dozent
        ref="wyss_g"><nachname>Wyss</nachname>, <vorname>Georg von</vorname>,
        <grad>O</grad></dozent> <thema>Ueber das römische Helvetien</thema>
        <zeit>Do 11-12</zeit> <wochenstunden>1</wochenstunden></veranstaltung>

        <veranstaltung xml:id="v-12834"><nr>132</nr> <dozent
        ref="meyer-knonau_g"><nachname>Meyer von Knonau</nachname>,
        <vorname>Gerold</vorname>, <grad>O</grad></dozent> <thema>Geschichte
        der Völkerwanderung</thema> <zeit>Di-Do 7-8</zeit>
        <wochenstunden>3</wochenstunden></veranstaltung>

        <veranstaltung xml:id="v-12835"><nr>133</nr> <dozent
        ref="meyer-knonau_g"><nachname>Meyer von Knonau</nachname>,
        <vorname>Gerold</vorname>, <grad>O</grad></dozent> <thema>Geschichte
        der neuesten Zeit seit 1815</thema> <zeit>Di-Do 8-9</zeit>
        <wochenstunden>3</wochenstunden></veranstaltung>

        <veranstaltung xml:id="v-12836"><nr>134</nr> <dozent
        ref="honegger_jj"><nachname>Honegger</nachname>, <vorname>Johann
        Jacob</vorname>, <grad>EO</grad></dozent> <thema>Geschichte des
        achtzehnten Jahrhunderts</thema> <zeit>Mo 8-10, Di 9-10</zeit>
        <wochenstunden>3</wochenstunden></veranstaltung>

        <veranstaltung xml:id="v-12837"><nr>135</nr> <dozent
        ref="wyss_g"><nachname>Wyss</nachname>, <vorname>Georg von</vorname>,
        <grad>O</grad></dozent> <thema>Geschichte der Schweiz, II. Theil (17.
        bis 19. Jahrhundert)</thema> <zeit>Mo, Di, Do, Fr 10-11</zeit>
        <wochenstunden>4</wochenstunden></veranstaltung>

        <veranstaltung xml:id="v-12838"><nr>136</nr> <dozent
        ref="voegelin_fs"><nachname>Vögelin</nachname>, <vorname>Friedrich
        Salomon</vorname>, <grad>O</grad></dozent> <thema>Schweizerische
        Kulturgeschichte von den ältesten Zeiten bis zum XV.
        Jahrhundert</thema> <zeit>Mo, Di, Do 14-15</zeit>
        <wochenstunden>3</wochenstunden></veranstaltung>

        <veranstaltung xml:id="v-12839"><nr>137</nr> <dozent
        ref="daendliker_k"><nachname>Dändliker</nachname>,
        <vorname>Karl</vorname>, <grad>PD</grad></dozent> <thema>Zeit- und
        Kulturbilder aus der Schweizergeschichte von 1500-1800</thema>
        <wochenstunden>1</wochenstunden>
        <ort>Polytechnikum</ort></veranstaltung>

        <veranstaltung xml:id="v-12840"><nr>138</nr> <dozent
        ref="wyss_g"><nachname>Wyss</nachname>, <vorname>Georg von</vorname>,
        <grad>O</grad></dozent> <thema>Geschichte des Kantons Zürich</thema>
        <zeit>Di, Fr 11-12</zeit>
        <wochenstunden>2</wochenstunden></veranstaltung>

        <veranstaltung xml:id="v-12841"><nr>139</nr> <dozent
        ref="voegelin_fs"><nachname>Vögelin</nachname>, <vorname>Friedrich
        Salomon</vorname>, <grad>O</grad></dozent> <thema>Geschichte der
        neuern Kunst</thema> <zeit>Mo, Do 15-16, Fr 14-15</zeit>
        <wochenstunden>3</wochenstunden></veranstaltung>

        <veranstaltung xml:id="v-12842"><nr>140</nr> <dozent
        ref="rahn_jr"><nachname>Rahn</nachname>, <vorname>Johann
        Rudolf</vorname>, <grad>EO</grad></dozent> <thema>Geschichte der
        italienischen Malerei</thema>
        <wochenstunden>3</wochenstunden></veranstaltung>

        <veranstaltung xml:id="v-12843"><nr>141a</nr> <dozent
        ref="mueller_j"><nachname>Müller</nachname>, <vorname>Jakob</vorname>,
        <grad>O</grad></dozent> <thema>Historisches Seminar:
        Universalhistorisches Conversatorium und Repetitorium</thema>
        <wochenstunden>2</wochenstunden></veranstaltung>

        <veranstaltung xml:id="v-12844"><nr>141b</nr> <dozent
        ref="meyer-knonau_g"><nachname>Meyer von Knonau</nachname>,
        <vorname>Gerold</vorname>, <grad>O</grad></dozent> <thema>Historisches
        Seminar: Kritisch-historische Uebungen (über Adam von Bremen, nach der
        Separatausgabe von 1876)<anmerkung>Adami gesta Hammaburgensis
        ecclesiae pontificum, ex recensione Lappenbergii in usum scholarum
        historicis recusa, Hannover: Hahn, 1876 (Monumenta Germaniae
        Historica, Scriptores 7; Scriptores rerum Germanicarum in usum
        scholarum separatim editi 2).</anmerkung></thema> <zeit>Do
        16-18</zeit> <wochenstunden>2</wochenstunden></veranstaltung>

        <veranstaltung xml:id="v-12845"><nr>141c</nr> <dozent
        ref="wyss_g"><nachname>Wyss</nachname>, <vorname>Georg von</vorname>,
        <grad>O</grad></dozent> <thema>Historisches Seminar: Quellenlektüre
        und Uebungen</thema> <zeit>Mo, Mi 11-12</zeit>
        <wochenstunden>2</wochenstunden></veranstaltung>

        <veranstaltung xml:id="v-12846"><nr>141d</nr> <dozent
        ref="voegelin_fs"><nachname>Vögelin</nachname>, <vorname>Friedrich
        Salomon</vorname>, <grad>O</grad></dozent> <thema>Historisches
        Seminar: Kulturgeschichtliche Uebungen (Chronik des Johannes von
        Winterthur, nach der Ausgabe von G. v. Wyss)<anmerkung>Johannis
        Vitodurani Chronicon: Die Chronik des Minoriten Johannes von
        Winterthur, hg. von Georg von Wyss, Zürich: Ulrich,
        1856.</anmerkung></thema>
        <wochenstunden>2</wochenstunden></veranstaltung>

        <veranstaltung xml:id="v-12847"><nr>141e</nr> <dozent
        ref="rahn_jr"><nachname>Rahn</nachname>, <vorname>Johann
        Rudolf</vorname>, <grad>EO</grad></dozent> <thema>Historisches
        Seminar: Kunstgeschichtliche Uebungen und Besprechungen mit
        Excursionen</thema> <wochenstunden>2</wochenstunden></veranstaltung>
      </sachgruppe>
    </sachgruppe>

    <sachgruppe>
      <titel>Mathematisch-naturwissenschaftliche Section</titel>

      <veranstaltung xml:id="v-12848"><nr>142</nr> <dozent
      ref="denzler_w"><nachname>Denzler</nachname>,
      <vorname>Wilhelm</vorname>, <grad>EO</grad></dozent> <thema>Ebene und
      sphärische Trigonometrie</thema>
      <wochenstunden>3</wochenstunden></veranstaltung>

      <veranstaltung xml:id="v-12849"><nr>143</nr> <dozent
      ref="weith_h"><nachname>Weith</nachname>, <vorname>Heinrich</vorname>,
      <grad>PD</grad></dozent> <thema>Algebraische Analysis</thema>
      <wochenstunden>2</wochenstunden></veranstaltung>

      <veranstaltung xml:id="v-12850"><nr>144</nr> <dozent
      ref="hug_jc"><nachname>Hug</nachname>, <vorname>Johann Caspar</vorname>,
      <grad>PD</grad></dozent> <thema>Algebraische Analysis und spezielle
      Einleitung in die Differentialrechnung</thema>
      <wochenstunden>3</wochenstunden></veranstaltung>

      <veranstaltung xml:id="v-12851"><nr>145</nr> <dozent
      ref="denzler_w"><nachname>Denzler</nachname>,
      <vorname>Wilhelm</vorname>, <grad>EO</grad></dozent>
      <thema>Differential- und Integralrechnung, inbegriffen algebraische
      Analysis</thema> <wochenstunden>3</wochenstunden></veranstaltung>

      <veranstaltung xml:id="v-12852"><nr>146</nr> <dozent
      ref="weith_h"><nachname>Weith</nachname>, <vorname>Heinrich</vorname>,
      <grad>PD</grad></dozent> <thema>Repetitorium der Differential- und
      Integralrechnung</thema>
      <wochenstunden>2</wochenstunden></veranstaltung>

      <veranstaltung xml:id="v-12853"><nr>147</nr> <dozent
      ref="meyer-keyser_a"><nachname>Meyer-Keyser</nachname>,
      <vorname>Arnold</vorname>, <grad>O</grad></dozent> <thema>Höhere
      Algebra</thema> <zeit>Di, Mi, Fr 8-9</zeit>
      <wochenstunden>3</wochenstunden></veranstaltung>

      <veranstaltung xml:id="v-12854"><nr>148</nr> <dozent
      ref="meyer-keyser_a"><nachname>Meyer-Keyser</nachname>,
      <vorname>Arnold</vorname>, <grad>O</grad></dozent>
      <thema>Zahlentheorie</thema> <zeit>Mo-Do 9-10</zeit>
      <wochenstunden>4</wochenstunden></veranstaltung>

      <veranstaltung xml:id="v-12855"><nr>149</nr> <dozent
      ref="denzler_w"><nachname>Denzler</nachname>,
      <vorname>Wilhelm</vorname>, <grad>EO</grad></dozent> <thema>Descriptive
      Geometrie, I. Theil</thema>
      <wochenstunden>3</wochenstunden></veranstaltung>

      <veranstaltung xml:id="v-12856"><nr>150</nr> <dozent
      ref="denzler_w"><nachname>Denzler</nachname>,
      <vorname>Wilhelm</vorname>, <grad>EO</grad></dozent> <thema>Descriptive
      Geometrie, II. Theil</thema>
      <wochenstunden>3</wochenstunden></veranstaltung>

      <veranstaltung xml:id="v-12857"><nr>151</nr> <dozent
      ref="weilenmann_a"><nachname>Weilenmann</nachname>,
      <vorname>August</vorname>, <grad>PD</grad></dozent> <thema>Descriptive
      Geometrie, I. Kurs</thema>
      <wochenstunden>2</wochenstunden></veranstaltung>

      <veranstaltung xml:id="v-12858"><nr>152</nr> <dozent
      ref="weilenmann_a"><nachname>Weilenmann</nachname>,
      <vorname>August</vorname>, <grad>PD</grad></dozent> <thema>Descriptive
      Geometrie, II. Kurs</thema>
      <wochenstunden>2</wochenstunden></veranstaltung>

      <veranstaltung xml:id="v-12859"><nr>153</nr> <dozent
      ref="weith_h"><nachname>Weith</nachname>, <vorname>Heinrich</vorname>,
      <grad>PD</grad></dozent> <thema>Kugelfunktionen mit Anwendungen</thema>
      <wochenstunden>2</wochenstunden></veranstaltung>

      <veranstaltung xml:id="v-12860"><nr>154</nr> <dozent
      ref="hug_jc"><nachname>Hug</nachname>, <vorname>Johann Caspar</vorname>,
      <grad>PD</grad></dozent> <thema>Methodik des geometrischen und
      mathematisch-geographischen Unterrichts in der Sekundarschule
      (Fortsetzung)</thema> <wochenstunden>2</wochenstunden></veranstaltung>

      <veranstaltung xml:id="v-12861"><nr>155</nr> <dozent
      ref="meyer-keyser_a"><nachname>Meyer-Keyser</nachname>,
      <vorname>Arnold</vorname>, <grad>O</grad></dozent>
      <thema>Mechanik</thema> <wochenstunden>3</wochenstunden></veranstaltung>

      <veranstaltung xml:id="v-12862"><nr>156</nr> <dozent
      ref="weilenmann_a"><nachname>Weilenmann</nachname>,
      <vorname>August</vorname>, <grad>PD</grad></dozent> <thema>Kosmische
      Physik (physikalischer Theil)</thema>
      <wochenstunden>2</wochenstunden></veranstaltung>

      <veranstaltung xml:id="v-12863"><nr>157</nr> <dozent
      ref="wolf_jr"><nachname>Wolf</nachname>, <vorname>Johann
      Rudolf</vorname>, <grad>EO</grad></dozent> <thema>Theorie der
      Doppelsterne</thema> <zeit>Mi 11-12</zeit>
      <wochenstunden>1</wochenstunden>
      <ort>Polytechnikum</ort></veranstaltung>

      <veranstaltung xml:id="v-12864"><nr>158</nr> <dozent
      ref="mousson_a"><nachname>Mousson</nachname>, <vorname>Albert</vorname>,
      <grad>O</grad></dozent> <thema>Experimental-Physik, II. Theil</thema>
      <zeit>Mo, Di, Do, Fr 10-11</zeit> <wochenstunden>4</wochenstunden>
      <ort>Polytechnikum</ort></veranstaltung>

      <veranstaltung xml:id="v-12865"><nr>159</nr> <dozent
      ref="mousson_a"><nachname>Mousson</nachname>, <vorname>Albert</vorname>,
      <grad>O</grad></dozent> <thema>Repetitorium</thema>
      <wochenstunden>1</wochenstunden>
      <ort>Polytechnikum</ort></veranstaltung>

      <veranstaltung xml:id="v-12866"><nr>160</nr> <dozent
      ref="hofmeister_rh"><nachname>Hofmeister</nachname>, <vorname>Rudolf
      Heinrich</vorname>, <grad>PD</grad></dozent> <thema>Experimental-Physik,
      II. Theil, Optik und Elektrizität</thema> <zeit>Mo, Di, Do, Fr
      10-11</zeit> <wochenstunden>4</wochenstunden></veranstaltung>

      <veranstaltung xml:id="v-12867"><nr>161</nr> <dozent
      ref="hofmeister_rh"><nachname>Hofmeister</nachname>, <vorname>Rudolf
      Heinrich</vorname>, <grad>PD</grad></dozent> <thema>Repetitorium über
      Optik und Elektrizität mit praktischen Uebungen, an der
      Lehramtsschule</thema> <wochenstunden>3</wochenstunden></veranstaltung>

      <veranstaltung xml:id="v-12868"><nr>162</nr> <dozent
      ref="kleiner_a"><nachname>Kleiner</nachname>, <vorname>Alfred</vorname>,
      <grad>PD</grad></dozent> <thema>Spectralanalyse</thema>
      <wochenstunden>1</wochenstunden></veranstaltung>

      <veranstaltung xml:id="v-12869"><nr>163</nr> <dozent
      ref="tobler_a"><nachname>Tobler</nachname>, <vorname>Adolf</vorname>,
      <grad>PD</grad></dozent> <thema>Telegraphie und Signalwesen der
      Eisenbahnen</thema> <wochenstunden>1</wochenstunden></veranstaltung>

      <veranstaltung xml:id="v-12870"><nr>164</nr> <dozent
      ref="weith_w"><nachname>Weith</nachname>, <vorname>Wilhelm</vorname>,
      <grad>O</grad></dozent> <thema>Allgemeine Chemie</thema> <zeit>Mi
      15-17</zeit> <wochenstunden>2</wochenstunden></veranstaltung>

      <veranstaltung xml:id="v-12871"><nr>165</nr> <dozent
      ref="abeljanz_h"><nachname>Abeljanz</nachname>,
      <vorname>Haruthiun</vorname>, <grad>PD</grad></dozent>
      <thema>Repetitorium der unorganischen Chemie, ohne Examinatorium</thema>
      <wochenstunden>2</wochenstunden></veranstaltung>

      <veranstaltung xml:id="v-12872"><nr>166</nr> <dozent
      ref="abeljanz_h"><nachname>Abeljanz</nachname>,
      <vorname>Haruthiun</vorname>, <grad>PD</grad></dozent>
      <thema>Analytische Chemie mit Berücksichtigung der
      physiologisch-chemischen Analyse</thema>
      <wochenstunden>2</wochenstunden></veranstaltung>

      <veranstaltung xml:id="v-12873"><nr>167</nr> <dozent
      ref="merz_v"><nachname>Merz</nachname>, <vorname>Viktor</vorname>,
      <grad>O</grad></dozent> <thema>Organische Chemie</thema> <zeit>Mo-Do
      11-12, Fr 10-12</zeit> <wochenstunden>6</wochenstunden></veranstaltung>

      <veranstaltung xml:id="v-12874"><nr>168</nr> <dozent
      ref="weith_w"><nachname>Weith</nachname>, <vorname>Wilhelm</vorname>,
      <grad>O</grad></dozent> <thema>Reaktionen der organischen Chemie</thema>
      <wochenstunden>2</wochenstunden></veranstaltung>

      <veranstaltung xml:id="v-12875"><nr>169</nr> <dozent
      ref="schmid_w"><nachname>Schmid</nachname>, <vorname>Werner</vorname>,
      <grad>PD</grad></dozent> <thema>Ausgewählte Capitel der technischen
      Chemie, I. Theil</thema>
      <wochenstunden>2</wochenstunden></veranstaltung>

      <veranstaltung xml:id="v-12876"><nr>170</nr> <dozent
      ref="schmid_w"><nachname>Schmid</nachname>, <vorname>Werner</vorname>,
      <grad>PD</grad></dozent> <thema>Chemie der Nahrungsgewerbe</thema>
      <wochenstunden>1</wochenstunden></veranstaltung>

      <veranstaltung xml:id="v-12877"><nr>171</nr> <dozent
      ref="gretillat_a"><nachname>Gretillat</nachname>,
      <vorname>August</vorname>, <grad>PD</grad></dozent> <thema>Metallurgie,
      I. le fer et l'acier</thema></veranstaltung>

      <veranstaltung xml:id="v-12878"><nr>172</nr> <dozent
      ref="annaheim_j"><nachname>Annaheim</nachname>,
      <vorname>Joseph</vorname>, <grad>PD</grad></dozent> <thema>Physikalische
      Chemie</thema> <wochenstunden>1</wochenstunden></veranstaltung>

      <veranstaltung xml:id="v-12879"><nr>173</nr> <dozent
      ref="weith_w"><nachname>Weith</nachname>, <vorname>Wilhelm</vorname>,
      <grad>O</grad></dozent> <thema>Geschichte der neueren chemischen
      Theorien</thema> <wochenstunden>2</wochenstunden></veranstaltung>

      <veranstaltung xml:id="v-12880"><nr>174</nr> <dozent
      ref="weith_w"><nachname>Weith</nachname>, <vorname>Wilhelm</vorname>,
      <grad>O</grad></dozent> <thema>Chemische Uebungen für
      Lehramtscandidaten</thema> <zeit>Di</zeit></veranstaltung>

      <veranstaltung xml:id="v-12881"><nr>175</nr> <dozent
      ref="merz_v"><nachname>Merz</nachname>, <vorname>Viktor</vorname>,
      <grad>O</grad></dozent> <thema>Uebungen im Laboratorium, speciell für
      Mediciner</thema> <wochenstunden>10</wochenstunden></veranstaltung>

      <veranstaltung xml:id="v-12882"><nr>176</nr> <dozent
      ref="merz_v"><nachname>Merz</nachname>, <vorname>Viktor</vorname>,
      <grad>O</grad></dozent> <thema>Chemische Arbeiten im
      Laboratorium</thema> <zeit>Mo-Sa</zeit></veranstaltung>

      <veranstaltung xml:id="v-12883"><nr>177</nr> <dozent
      ref="merz_v"><nachname>Merz</nachname>, <vorname>Viktor</vorname>,
      <grad>O</grad></dozent> <dozent
      ref="weith_w"><nachname>Weith</nachname>, <vorname>Wilhelm</vorname>,
      <grad>O</grad></dozent> <thema>Vollpraktikum für Vorgerücktere:
      Einführung in die selbstständige chemische Forschung</thema>
      <zeit>Mo-Sa</zeit></veranstaltung>

      <veranstaltung xml:id="v-12884"><nr>178</nr> <dozent
      ref="kenngott_jga"><nachname>Kenngott</nachname>, <vorname>Johann Gustav
      Adolf</vorname>, <grad>O</grad>, <funktion>Dekan/P2</funktion></dozent>
      <thema>Theoretische Krystallographie</thema>
      <wochenstunden>3</wochenstunden>
      <ort>Polytechnikum</ort></veranstaltung>

      <veranstaltung xml:id="v-12885"><nr>179</nr> <dozent
      ref="heim_a"><nachname>Heim</nachname>, <vorname>Albert</vorname>,
      <grad>EO</grad></dozent> <thema>Vorbereitungscurs für die Geologie, den
      Bedürfnissen der Lehramtsschule entsprechend</thema>
      <wochenstunden>1-2</wochenstunden></veranstaltung>

      <veranstaltung xml:id="v-12886"><nr>180</nr> <dozent
      ref="heim_a"><nachname>Heim</nachname>, <vorname>Albert</vorname>,
      <grad>EO</grad></dozent> <thema>Die vulkanischen Erscheinungen und
      Theorien</thema> <wochenstunden>2</wochenstunden>
      <ort>Polytechnikum</ort></veranstaltung>

      <veranstaltung xml:id="v-12887"><nr>181</nr> <dozent
      ref="heim_a"><nachname>Heim</nachname>, <vorname>Albert</vorname>,
      <grad>EO</grad></dozent> <thema>Gletscher und Eiszeit</thema>
      <wochenstunden>1</wochenstunden>
      <ort>Polytechnikum</ort></veranstaltung>

      <veranstaltung xml:id="v-12888"><nr>182</nr> <dozent
      ref="mayer-eymar_k"><nachname>Mayer-Eymar</nachname>,
      <vorname>Karl</vorname>, <grad>EO</grad></dozent> <thema>Stratigraphie
      der Kreideformation</thema> <zeit>Di, Do 11-12</zeit>
      <wochenstunden>2</wochenstunden>
      <ort>Polytechnikum</ort></veranstaltung>

      <veranstaltung xml:id="v-12889"><nr>183</nr> <dozent
      ref="heim_a"><nachname>Heim</nachname>, <vorname>Albert</vorname>,
      <grad>EO</grad></dozent> <thema>Geologische Excursionen</thema>
      <ort>Polytechnikum</ort></veranstaltung>

      <veranstaltung xml:id="v-12890"><nr>184</nr> <dozent
      ref="heim_a"><nachname>Heim</nachname>, <vorname>Albert</vorname>,
      <grad>EO</grad></dozent> <thema>Uebungen im Terrainmodelliren</thema>
      <wochenstunden>4</wochenstunden>
      <ort>Polytechnikum</ort></veranstaltung>

      <veranstaltung xml:id="v-12891"><nr>185</nr> <dozent
      ref="dodel_a"><nachname>Dodel</nachname>, <vorname>Arnold</vorname>,
      <grad>PD</grad></dozent> <thema>Repetitorium der allgemeinen Botanik
      (Anatomie und Entwicklungsgeschichte)</thema>
      <wochenstunden>2</wochenstunden></veranstaltung>

      <veranstaltung xml:id="v-12892"><nr>186</nr> <dozent
      ref="cramer_c"><nachname>Cramer</nachname>, <vorname>Carl</vorname>,
      <grad>PD</grad></dozent> <thema>Pflanzenphysiologie mit
      Experimenten</thema> <wochenstunden>2</wochenstunden>
      <ort>Polytechnikum</ort></veranstaltung>

      <veranstaltung xml:id="v-12893"><nr>187</nr> <dozent
      ref="dodel_a"><nachname>Dodel</nachname>, <vorname>Arnold</vorname>,
      <grad>PD</grad></dozent> <thema>Pflanzenphysiologisches Privatissimum
      (Mikroskopischer Curs für Vorgerücktere)</thema></veranstaltung>

      <veranstaltung xml:id="v-12894"><nr>188</nr> <dozent
      ref="cramer_c"><nachname>Cramer</nachname>, <vorname>Carl</vorname>,
      <grad>PD</grad></dozent> <thema>Mikroskopische Uebungen für Anfänger und
      Vorgerücktere</thema> <wochenstunden>2-4</wochenstunden>
      <ort>Polytechnikum</ort></veranstaltung>

      <veranstaltung xml:id="v-12895"><nr>189</nr> <dozent
      ref="dodel_a"><nachname>Dodel</nachname>, <vorname>Arnold</vorname>,
      <grad>PD</grad></dozent> <thema>Mikroskopische Demonstrationen und
      praktische Uebungen, in Gruppen</thema>
      <wochenstunden>2</wochenstunden></veranstaltung>

      <veranstaltung xml:id="v-12896"><nr>190</nr> <dozent
      ref="dodel_a"><nachname>Dodel</nachname>, <vorname>Arnold</vorname>,
      <grad>PD</grad></dozent> <thema>Einführung in die spezielle Botanik
      unter Berücksichtigung der medicinischen Nutzpflanzen, verbunden mit
      Demonstrationen im botanischen Garten</thema>
      <wochenstunden>3</wochenstunden></veranstaltung>

      <veranstaltung xml:id="v-12897"><nr>191</nr> <dozent
      ref="heer_o"><nachname>Heer</nachname>, <vorname>Oswald</vorname>,
      <grad>O</grad></dozent> <thema>Specielle Botanik mit besonderer
      Berücksichtigung der officinellen und der Nutzgewächse</thema>
      <zeit>Mo-Fr 5-6</zeit> <wochenstunden>5</wochenstunden></veranstaltung>

      <veranstaltung xml:id="v-12898"><nr>192</nr> <dozent
      ref="dodel_a"><nachname>Dodel</nachname>, <vorname>Arnold</vorname>,
      <grad>PD</grad></dozent> <thema>Uebungen im Pflanzenbestimmen</thema>
      <wochenstunden>2</wochenstunden></veranstaltung>

      <veranstaltung xml:id="v-12899"><nr>193</nr> <dozent
      ref="dodel_a"><nachname>Dodel</nachname>, <vorname>Arnold</vorname>,
      <grad>PD</grad></dozent> <thema>Botanische Excursionen mit specieller
      Berücksichtigung physiologischer Erscheinungen</thema>
      <zeit>Sa</zeit></veranstaltung>

      <veranstaltung xml:id="v-12900"><nr>194</nr> <dozent
      ref="keller_c"><nachname>Keller</nachname>, <vorname>Conrad</vorname>,
      <grad>PD</grad></dozent> <thema>Vergleichende Anatomie</thema>
      <wochenstunden>4</wochenstunden></veranstaltung>

      <veranstaltung xml:id="v-12901"><nr>195</nr> <dozent
      ref="keller_c"><nachname>Keller</nachname>, <vorname>Conrad</vorname>,
      <grad>PD</grad></dozent> <thema>Anatomie und Physiologie des Menschen,
      für die Lehramtscandidaten</thema>
      <wochenstunden>3</wochenstunden></veranstaltung>

      <veranstaltung xml:id="v-12902"><nr>196</nr> <dozent
      ref="menzel_a"><nachname>Menzel</nachname>, <vorname>August</vorname>,
      <grad>PD</grad></dozent> <thema>Naturgeschichte der Wirbelthiere mit
      Berücksichtigung der fossilen Formen</thema>
      <wochenstunden>3</wochenstunden></veranstaltung>

      <veranstaltung xml:id="v-12903"><nr>197</nr> <dozent
      ref="keller_c"><nachname>Keller</nachname>, <vorname>Conrad</vorname>,
      <grad>PD</grad></dozent> <thema>Zoologischer Uebungscurs</thema>
      <wochenstunden>2</wochenstunden></veranstaltung>

      <veranstaltung xml:id="v-12904"><nr>198</nr> <dozent
      ref="menzel_a"><nachname>Menzel</nachname>, <vorname>August</vorname>,
      <grad>PD</grad></dozent> <thema>Ueber Thierstaaten mit besonderer
      Beziehung auf den Bienenstaat</thema>
      <wochenstunden>2</wochenstunden></veranstaltung>

      <veranstaltung xml:id="v-12905"><nr>199</nr> <dozent
      ref="egli_jj"><nachname>Egli</nachname>, <vorname>Johann
      Jakob</vorname>, <grad>PD</grad></dozent> <thema>Geschichte der Erdkunde
      der Neuzeit</thema> <wochenstunden>1</wochenstunden></veranstaltung>
    </sachgruppe>
  </sachgruppe>
</vv>
